{
  "cost": 80,
  "elem": "glimmeringtales:earth",
  "focus": 40,
  "graph": {
    "flows": [
      "L->E",
      "E->F",
      "F->S",
      "S->O",
      "O->T",
      "T->L"
    ],
    "map": {
      "E": "glimmeringtales:earth",
      "F": "glimmeringtales:flame",
      "L": "glimmeringtales:life",
      "O": "glimmeringtales:ocean",
      "S": "glimmeringtales:snow",
      "T": "glimmeringtales:thunder"
    }
  },
  "maxConsumeTick": 0,
  "mob": {
    "idealRange": 5.0,
    "maxUseTick": 40,
    "timeFactor": 1.0
  },
  "spell": "glimmeringtales:earthquake",
  "tooltip": {
    "list": [
      {
        "id": "l2magic:damage",
        "reg": "l2magic:processor"
      },
      {
        "id": "glimmeringtales:knock_block",
        "reg": "l2magic:configured_engine"
      }
    ]
  }
}